esdocs/__init__.py
esdocs/controller.py
esdocs/exceptions.py
esdocs/policies.py
esdocs/run.py
esdocs/serializer.py
esdocs/utils.py
esdocs/contrib/__init__.py
esdocs/contrib/esdjango/__init__.py
esdocs/contrib/esdjango/apps.py
esdocs/contrib/esdjango/compatibility.py
esdocs/contrib/esdjango/pagination.py
esdocs/contrib/esdjango/run.py
esdocs/contrib/esdjango/serializer.py
esdocs/contrib/esdjango/settings.py
esdocs/contrib/esdjango/signals.py
esdocs/contrib/postgresql/__init__.py
esdocs/contrib/postgresql/compatibility.py
esdocs-0.6.2.dist-info/LICENSE
esdocs-0.6.2.dist-info/METADATA
esdocs-0.6.2.dist-info/WHEEL
esdocs-0.6.2.dist-info/entry_points.txt
esdocs-0.6.2.dist-info/top_level.txt
esdocs-0.6.2.dist-info/RECORD
