Metadata-Version: 2.1
Name: esdocs
Version: 0.6.2
Summary: Serialization & bulk indexing package for Elasticsearch; based on elasticsearch-dsl.py, supports multi-processing, Django
Home-page: https://github.com/jaddison/esdocs
Author: jaddison
Author-email: addi00+github.com@gmail.com
License: MIT
Keywords: elasticsearch django multiprocessing gevent gipc asynchronous bulk index serialization
Platform: UNKNOWN
Classifier: Development Status :: 4 - Beta
Classifier: Environment :: Web Environment
Classifier: Framework :: Django
Classifier: Intended Audience :: Developers
Classifier: Intended Audience :: Information Technology
Classifier: Intended Audience :: System Administrators
Classifier: License :: OSI Approved :: MIT License
Classifier: Operating System :: MacOS :: MacOS X
Classifier: Operating System :: POSIX
Classifier: Programming Language :: Python
Classifier: Programming Language :: Python :: 3 :: Only
Classifier: Programming Language :: Python :: 3
Classifier: Programming Language :: Python :: 3.4
Classifier: Programming Language :: Python :: 3.5
Classifier: Programming Language :: Python :: 3.6
Classifier: Programming Language :: Python :: 3.7
Classifier: Topic :: Database
Classifier: Topic :: System :: Networking
Classifier: Topic :: Internet :: WWW/HTTP :: Indexing/Search
Requires-Python: >=3.4
Requires-Dist: elasticsearch-dsl (<8,>=7)
Provides-Extra: gevent
Requires-Dist: gevent ; extra == 'gevent'
Requires-Dist: gipc ; extra == 'gevent'
